h2o_lightwave_web/__init__.py
h2o_lightwave_web/version.py
h2o_lightwave_web/www/favicon.ico
h2o_lightwave_web/www/index.html
h2o_lightwave_web/www/logo192.png
h2o_lightwave_web/www/logo512.png
h2o_lightwave_web/www/manifest.json
h2o_lightwave_web/www/robots.txt
h2o_lightwave_web/www/wave-static/1c-3f7bb63f.js
h2o_lightwave_web/www/wave-static/1c.js-880a5fb5.js
h2o_lightwave_web/www/wave-static/Inter-Black-8b21d5be.woff
h2o_lightwave_web/www/wave-static/Inter-Black-fc10113c.woff2
h2o_lightwave_web/www/wave-static/Inter-Bold-3e242080.woff
h2o_lightwave_web/www/wave-static/Inter-Bold-c63158ba.woff2
h2o_lightwave_web/www/wave-static/Inter-ExtraBold-307d9809.woff2
h2o_lightwave_web/www/wave-static/Inter-ExtraBold-f053602c.woff
h2o_lightwave_web/www/wave-static/Inter-ExtraLight-015dad27.woff
h2o_lightwave_web/www/wave-static/Inter-ExtraLight-b6cd094a.woff2
h2o_lightwave_web/www/wave-static/Inter-Light-36b86832.woff2
h2o_lightwave_web/www/wave-static/Inter-Light-4871aed0.woff
h2o_lightwave_web/www/wave-static/Inter-Medium-1b498b95.woff2
h2o_lightwave_web/www/wave-static/Inter-Medium-53deda46.woff
h2o_lightwave_web/www/wave-static/Inter-Regular-d612f121.woff2
h2o_lightwave_web/www/wave-static/Inter-Regular-ef1f23c0.woff
h2o_lightwave_web/www/wave-static/Inter-SemiBold-15226129.woff2
h2o_lightwave_web/www/wave-static/Inter-SemiBold-653fed7a.woff
h2o_lightwave_web/www/wave-static/Inter-Thin-77d96c1c.woff2
h2o_lightwave_web/www/wave-static/Inter-Thin-e6bced8e.woff
h2o_lightwave_web/www/wave-static/LocalizationProvider-dfbd5f26.js
h2o_lightwave_web/www/wave-static/Paper-10489cb3.js
h2o_lightwave_web/www/wave-static/abnf-13e3d3e9.js
h2o_lightwave_web/www/wave-static/abnf.js-4710a9b6.js
h2o_lightwave_web/www/wave-static/accesslog-0333fe45.js
h2o_lightwave_web/www/wave-static/accesslog.js-c69c4014.js
h2o_lightwave_web/www/wave-static/actionscript-970abe00.js
h2o_lightwave_web/www/wave-static/actionscript.js-a23662e0.js
h2o_lightwave_web/www/wave-static/ada-29abd822.js
h2o_lightwave_web-1.7.7.dist-info/METADATA
h2o_lightwave_web-1.7.7.dist-info/WHEEL
h2o_lightwave_web-1.7.7.dist-info/licenses/LICENSE
h2o_lightwave_web-1.7.7.dist-info/RECORD
