Metadata-Version: 2.4
Name: h2o_lightwave_web
Version: 1.7.7
Summary: Web assets package for H2O Lightwave apps.
Project-URL: Homepage, https://wave.h2o.ai/
Project-URL: Documentation, https://wave.h2o.ai/
Project-URL: Repository, https://github.com/h2oai/wave
Project-URL: Changelog, https://github.com/h2oai/wave/releases
Author-email: Martin Turoci <martin.turoci@h2o.ai>
License-Expression: Apache-2.0
License-File: LICENSE
Keywords: Data Science,Low code,Machine Learning,Realtime,UI
Classifier: Development Status :: 5 - Production/Stable
Classifier: Intended Audience :: Developers
Classifier: License :: OSI Approved :: Apache Software License
Classifier: Operating System :: OS Independent
Classifier: Programming Language :: Python :: 3
Classifier: Programming Language :: Python :: 3.8
Classifier: Programming Language :: Python :: 3.9
Classifier: Programming Language :: Python :: 3.10
Classifier: Programming Language :: Python :: 3.11
Classifier: Topic :: Communications :: Chat
Classifier: Topic :: Internet :: WWW/HTTP :: Dynamic Content
Classifier: Topic :: Scientific/Engineering :: Visualization
Classifier: Topic :: Software Development :: Libraries :: Application Frameworks
Classifier: Topic :: Software Development :: Widget Sets
Requires-Python: >=3.8
